[{"name":"environment_count","evidenceType":"number","typeFidelity":"precise"},{"name":"total_flows","evidenceType":"number","typeFidelity":"precise"},{"name":"total_agents","evidenceType":"number","typeFidelity":"precise"},{"name":"total_apps","evidenceType":"number","typeFidelity":"precise"},{"name":"total_resources","evidenceType":"number","typeFidelity":"precise"},{"name":"environments_with_drift","evidenceType":"number","typeFidelity":"precise"},{"name":"total_drift_units","evidenceType":"number","typeFidelity":"precise"}]